LICENSE
MANIFEST.in
README.md
pyproject.toml
requirements.txt
setup.py
clusopt_core/__init__.py
clusopt_core.egg-info/PKG-INFO
clusopt_core.egg-info/SOURCES.txt
clusopt_core.egg-info/dependency_links.txt
clusopt_core.egg-info/requires.txt
clusopt_core.egg-info/top_level.txt
clusopt_core/cluster/__init__.py
clusopt_core/cluster/__init__.pyi
clusopt_core/cluster/clustream/__init__.py
clusopt_core/cluster/clustream/bindings.cpp
clusopt_core/cluster/clustream/clustream.cpp
clusopt_core/cluster/clustream/clustream.hpp
clusopt_core/cluster/clustream/kernel.cpp
clusopt_core/cluster/clustream/kernel.hpp
clusopt_core/cluster/streamkm/__init__.py
clusopt_core/cluster/streamkm/bindings.cpp
clusopt_core/cluster/streamkm/wrapper.cpp
clusopt_core/cluster/streamkm/wrapper.hpp
clusopt_core/cluster/streamkm/original/DatasetFunctions.c
clusopt_core/cluster/streamkm/original/DatasetFunctions.h
clusopt_core/cluster/streamkm/original/LloydPlusPlus.c
clusopt_core/cluster/streamkm/original/LloydPlusPlus.h
clusopt_core/cluster/streamkm/original/Point.c
clusopt_core/cluster/streamkm/original/Point.h
clusopt_core/cluster/streamkm/original/StreamingCoreset.c
clusopt_core/cluster/streamkm/original/StreamingCoreset.h
clusopt_core/cluster/streamkm/original/TreeCoreset.c
clusopt_core/cluster/streamkm/original/TreeCoreset.h
clusopt_core/cluster/streamkm/original/featurepp.h
clusopt_core/cluster/streamkm/original/kMeansUtilityFunctions.c
clusopt_core/cluster/streamkm/original/kMeansUtilityFunctions.h
clusopt_core/cluster/streamkm/original/mt19937ar.c
clusopt_core/cluster/streamkm/original/mt19937ar.h
clusopt_core/metrics/__init__.py
clusopt_core/metrics/__init__.pyi
clusopt_core/metrics/dist_matrix.cpp
clusopt_core/metrics/silhouette.cpp
tests/test_dmatrix_and_sil.py