Metadata-Version: 2.1
Name: clusopt_core
Version: 1.1.7
Summary: Clustream, Streamkm++ and metrics utilities C/C++ bindings for python
Home-page: https://github.com/giuliano-oliveira/clusopt_core
Download-URL: https://github.com/giuliano-oliveira/clusopt_core/archive/v1.1.7.tar.gz
Author: Giuliano Oliveira De Macedo
Author-email: giuliano.llpinokio@gmail.com
License: GPLv3
Keywords: data-stream,clustering,silhouette
Classifier: Development Status :: 5 - Production/Stable
Classifier: Programming Language :: Python :: 3
Classifier: Programming Language :: C++
Classifier: License :: OSI Approved :: GNU General Public License v3 (GPLv3)
Classifier: Operating System :: OS Independent
Requires-Python: >=3.6
License-File: LICENSE
Requires-Dist: scikit-learn>=0.23.1
